pypido/__init__.py
pypido/__main__.py
pypido-0.0.1.dist-info/entry_points.txt
pypido-0.0.1.dist-info/WHEEL
pypido-0.0.1.dist-info/METADATA
pypido-0.0.1.dist-info/RECORD
