Metadata-Version: 2.1
Name: pypido
Version: 0.0.1
Summary: pypido - simple tool to create and publish Pypi packages (version 0.0.1 = not yet implemented!!!)
Home-page: https://pypi.org/project/pypido
Author: Carlo Alessandro Verre
Author-email: carlo.alessandro.verre@gmail.com
Requires-Python: >=3.6
Classifier: Programming Language :: Python :: 3
Classifier: Programming Language :: Python :: 3.6
Classifier: Development Status :: 1 - Planning
Classifier: Environment :: Console
Classifier: Intended Audience :: End Users/Desktop
Classifier: License :: OSI Approved :: GNU General Public License v3 or later (GPLv3+)
Classifier: Operating System :: POSIX :: Linux
Requires-Dist: flit >=3.4.0
